README.md
docsrag/__init__.py
docsrag/cli.py
docsrag/docs_loader.py
docsrag/embedding/__init__.py
docsrag/embedding/evaluation.py
docsrag/embedding/finetuning.py
docsrag/embedding/index.py
docsrag/embedding/utils.py
docsrag/evaluation_dataset_generator.py
docsrag/llm/__init__.py
docsrag/llm/model.py
docsrag/node_parser.py
docsrag/py.typed
docsrag/utils.py
docsrag-0.1.6.dist-info/METADATA
docsrag-0.1.6.dist-info/WHEEL
docsrag-0.1.6.dist-info/entry_points.txt
docsrag-0.1.6.dist-info/RECORD
